matomo_dl/__init__.py
matomo_dl/__main__.py
matomo_dl/__version__.py
matomo_dl/call_tree.py
matomo_dl/colored_diff.py
matomo_dl/errors.py
matomo_dl/gpg.py
matomo_dl/hashing.py
matomo_dl/matomo_config.py
matomo_dl/progress.py
matomo_dl/bundle/__init__.py
matomo_dl/bundle/extract.py
matomo_dl/bundle/fs_util.py
matomo_dl/bundle/info.py
matomo_dl/bundle/stat.py
matomo_dl/bundle/customisation/__init__.py
matomo_dl/bundle/customisation/autoload.py
matomo_dl/bundle/customisation/config.py
matomo_dl/bundle/customisation/duplicates.py
matomo_dl/bundle/customisation/manifest.py
matomo_dl/bundle/customisation/remove.py
matomo_dl/bundle/plugin/__init__.py
matomo_dl/distribution/__init__.py
matomo_dl/distribution/customisations.py
matomo_dl/distribution/file.py
matomo_dl/distribution/load_save.py
matomo_dl/distribution/lock.py
matomo_dl/distribution/version.py
matomo_dl/lock/__init__.py
matomo_dl/lock/general.py
matomo_dl/lock/matomo.py
matomo_dl/lock/plugin/__init__.py
matomo_dl/lock/plugin/git.py
matomo_dl/lock/plugin/versioned.py
matomo_dl/session/__init__.py
matomo_dl/session/caching_store.py
matomo_dl/session/store.py
matomo_dl-1.3.0.dist-info/LICENSE
matomo_dl-1.3.0.dist-info/METADATA
matomo_dl-1.3.0.dist-info/WHEEL
matomo_dl-1.3.0.dist-info/entry_points.txt
matomo_dl-1.3.0.dist-info/top_level.txt
matomo_dl-1.3.0.dist-info/RECORD
