Metadata-Version: 2.1
Name: matomo-dl
Version: 1.3.0
Summary: .
Home-page: UNKNOWN
Author: Opal Symes
Author-email: opal@catalyst.net.nz
License: GPLv3+
Platform: UNKNOWN
Requires-Python: >=3.6
Requires-Dist: attrs (~=18.2)
Requires-Dist: beautifulsoup4 (~=4.6)
Requires-Dist: cattrs (==0.9.0)
Requires-Dist: click (~=7.0)
Requires-Dist: click-log
Requires-Dist: colorama (==0.4.0)
Requires-Dist: lxml (~=4.2)
Requires-Dist: packaging (~=18.0)
Requires-Dist: requests (~=2.20)
Requires-Dist: toml (==0.10.0)
Provides-Extra: cache
Requires-Dist: requests-cache (==0.4.13) ; extra == 'cache'
